setup.cfg
setup.py
lightfm/__init__.py
lightfm/_lightfm_fast.py
lightfm/_lightfm_fast_no_openmp.c
lightfm/_lightfm_fast_openmp.c
lightfm/evaluation.py
lightfm/lightfm.py
lightfm.egg-info/PKG-INFO
lightfm.egg-info/SOURCES.txt
lightfm.egg-info/dependency_links.txt
lightfm.egg-info/requires.txt
lightfm.egg-info/top_level.txt
lightfm/datasets/__init__.py
lightfm/datasets/_common.py
lightfm/datasets/movielens.py
lightfm/datasets/stackexchange.py