Metadata-Version: 1.1
Name: lightfm
Version: 1.10
Summary: LightFM recommendation model
Home-page: https://github.com/lyst/lightfm
Author: Lyst Ltd (Maciej Kula)
Author-email: data@ly.st
License: MIT
Download-URL: https://github.com/lyst/lightfm/tarball/1.10
Platform: UNKNOWN
Classifier: Development Status :: 3 - Alpha
Classifier: License :: OSI Approved :: MIT License
Classifier: Topic :: Scientific/Engineering :: Artificial Intelligence
